nonebot_plugin_cfassistant/__init__.py
nonebot_plugin_cfassistant/changeRemind.py
nonebot_plugin_cfassistant/randomProblems.py
nonebot_plugin_cfassistant/updateContest.py
nonebot_plugin_cfassistant/updateUser.py
nonebot_plugin_cfassistant-1.4.dist-info/METADATA
nonebot_plugin_cfassistant-1.4.dist-info/WHEEL
nonebot_plugin_cfassistant-1.4.dist-info/top_level.txt
nonebot_plugin_cfassistant-1.4.dist-info/RECORD
